{
	"configurations" : 
	[
		{
			"directories" : 
			[
				{
					"build" : ".",
					"hasInstallRule" : true,
					"jsonFile" : "directory-.-417cd3d58ede8833f8db.json",
					"minimumCMakeVersion" : 
					{
						"string" : "3.12"
					},
					"projectIndex" : 0,
					"source" : ".",
					"targetIndexes" : 
					[
						0,
						1,
						2,
						3,
						4
					]
				}
			],
			"name" : "",
			"projects" : 
			[
				{
					"directoryIndexes" : 
					[
						0
					],
					"name" : "acs6121_team16_2025",
					"targetIndexes" : 
					[
						0,
						1,
						2,
						3,
						4
					]
				}
			],
			"targets" : 
			[
				{
					"directoryIndex" : 0,
					"id" : "acs6121_team16_2025_uninstall::@6890427a1f51a3e7e1df",
					"jsonFile" : "target-acs6121_team16_2025_uninstall-0b814b271971c0ce2110.json",
					"name" : "acs6121_team16_2025_uninstall",
					"projectIndex" : 0
				},
				{
					"directoryIndex" : 0,
					"id" : "ament_cmake_python_build_acs6121_team16_2025_modules_egg::@6890427a1f51a3e7e1df",
					"jsonFile" : "target-ament_cmake_python_build_acs6121_team16_2025_modules_egg-6f7408eea9e214e6cd6a.json",
					"name" : "ament_cmake_python_build_acs6121_team16_2025_modules_egg",
					"projectIndex" : 0
				},
				{
					"directoryIndex" : 0,
					"id" : "ament_cmake_python_symlink_acs6121_team16_2025_modules::@6890427a1f51a3e7e1df",
					"jsonFile" : "target-ament_cmake_python_symlink_acs6121_team16_2025_modules-702d5dbf8a2b577c317a.json",
					"name" : "ament_cmake_python_symlink_acs6121_team16_2025_modules",
					"projectIndex" : 0
				},
				{
					"directoryIndex" : 0,
					"id" : "cpp_executable::@6890427a1f51a3e7e1df",
					"jsonFile" : "target-cpp_executable-0c44e5d8841a2c6d5f4f.json",
					"name" : "cpp_executable",
					"projectIndex" : 0
				},
				{
					"directoryIndex" : 0,
					"id" : "uninstall::@6890427a1f51a3e7e1df",
					"jsonFile" : "target-uninstall-1aaf554e9fba10dd26e3.json",
					"name" : "uninstall",
					"projectIndex" : 0
				}
			]
		}
	],
	"kind" : "codemodel",
	"paths" : 
	{
		"build" : "/home/student/ros2_ws/build/acs6121_team16_2025",
		"source" : "/home/student/ros2_ws/src/acs6121_team16_2025"
	},
	"version" : 
	{
		"major" : 2,
		"minor" : 3
	}
}
